{
    "name": "Horizon Light",
    "semanticClass": "theme.horizon-light",
    "base24": {
        "base": [
            "#FDF0ED",
            "#403C3D",
            "#FADAD1",
            "#BDB3B1",
            "#DC3318",
            "#94E1B0",
            "#F6661E",
            "#1D8991",
            "#DA103F",
            "#F7939B",
            "#FBE0D9"
        ],
        "ansi": [
            "#FADAD1",
            "#F7939B",
            "#94E1B0",
            "#F6661E",
            "#DA103F",
            "#1D8991",
            "#DC3318",
            "#302C2D",
            "#F9CBBE",
            "#F7939B",
            "#94E1B0",
            "#FBE0D9",
            "#DA103F",
            "#1D8991",
            "#DC3318",
            "#201C1D"
        ],
        "brightOther": [
            "#FBE0D9",
            "#DA103F"
        ],
        "other": [
            "#F9CBBE75",
            "#201C1D1A",
            "#201C1D",
            "#F9CBBE70",
            "#FADAD1",
            "#FDF0ED",
            "#FDF0ED",
            "#FDF0ED"
        ]
    },
    "colors": {
        "terminal.background": "#FDF0ED",
        "terminal.foreground": "#403C3D",
        "terminal.ansiBrightBlack": "#F9CBBE",
        "terminal.ansiBrightRed": "#F7939B",
        "terminal.ansiBrightGreen": "#94E1B0",
        "terminal.ansiBrightYellow": "#FBE0D9",
        "terminal.ansiBrightBlue": "#DA103F",
        "terminal.ansiBrightMagenta": "#1D8991",
        "terminal.ansiBrightCyan": "#DC3318",
        "terminal.ansiBrightWhite": "#201C1D",
        "terminal.ansiBlack": "#FADAD1",
        "terminal.ansiRed": "#F7939B",
        "terminal.ansiGreen": "#94E1B0",
        "terminal.ansiYellow": "#F6661E",
        "terminal.ansiBlue": "#DA103F",
        "terminal.ansiMagenta": "#1D8991",
        "terminal.ansiCyan": "#DC3318",
        "terminal.ansiWhite": "#302C2D",
        "terminal.border": "#403C3D",
        "terminal.selectionBackground": "#FADAD1",
        "textBlockQuote.background": "#FDF0ED",
        "contrastBorder": "#FDF0ED",
        "focusBorder": "#BDB3B1",
        "foreground": "#403C3D",
        "selection.background": "#DA103F",
        "errorForeground": "#F7939B",
        "button.background": "#FDF0ED",
        "button.foreground": "#403C3D",
        "dropdown.background": "#FDF0ED",
        "dropdown.border": "#FDF0ED",
        "dropdown.foreground": "#403C3D",
        "input.background": "#FDF0ED",
        "input.foreground": "#403C3D",
        "input.border": "#FDF0ED",
        "input.placeholderForeground": "#BDB3B1",
        "inputOption.activeBorder": "#DA103F",
        "inputValidation.infoForeground": "#DA103F",
        "inputValidation.infoBackground": "#FDF0ED",
        "inputValidation.infoBorder": "#DA103F",
        "inputValidation.warningForeground": "#F6661E",
        "inputValidation.warningBackground": "#FDF0ED",
        "inputValidation.warningBorder": "#F6661E",
        "inputValidation.errorForeground": "#F7939B",
        "inputValidation.errorBackground": "#FDF0ED",
        "inputValidation.errorBorder": "#F7939B",
        "badge.foreground": "#403C3D",
        "badge.background": "#FADAD1",
        "progressBar.background": "#1D8991",
        "list.activeSelectionBackground": "#FADAD1",
        "list.activeSelectionForeground": "#403C3D",
        "list.dropBackground": "#FADAD1",
        "list.focusBackground": "#F9CBBE75",
        "list.highlightForeground": "#DC3318",
        "list.hoverBackground": "#F9CBBE75",
        "list.inactiveSelectionBackground": "#F9CBBE75",
        "list.warningForeground": "#F6661E",
        "list.errorForeground": "#F7939B",
        "activityBar.background": "#FDF0ED",
        "activityBar.inactiveForeground": "#BDB3B1",
        "activityBar.foreground": "#403C3D",
        "activityBar.activeBorder": "#1D899180",
        "activityBar.activeBackground": "#DA103F10",
        "activityBarBadge.background": "#1D8991",
        "activityBarBadge.foreground": "#FDF0ED",
        "sideBar.background": "#FDF0ED",
        "sideBarTitle.foreground": "#403C3D",
        "sideBarSectionHeader.background": "#FDF0ED",
        "sideBarSectionHeader.border": "#FDF0ED",
        "editorGroup.border": "#DA103F",
        "editorGroup.dropBackground": "#F9CBBE70",
        "editorGroupHeader.tabsBackground": "#FDF0ED",
        "tab.activeBackground": "#FDF0ED",
        "tab.activeForeground": "#403C3D",
        "tab.border": "#FDF0ED",
        "tab.activeBorderTop": "#1D899180",
        "tab.inactiveBackground": "#FDF0ED",
        "tab.inactiveForeground": "#BDB3B1",
        "editor.foreground": "#403C3D",
        "editor.background": "#FDF0ED",
        "editorLineNumber.foreground": "#BDB3B1",
        "editor.selectionBackground": "#FADAD1",
        "editor.selectionHighlightBackground": "#FADAD1",
        "editor.foldBackground": "#FDF0ED",
        "editor.wordHighlightBackground": "#DC331850",
        "editor.wordHighlightStrongBackground": "#94E1B050",
        "editor.findMatchBackground": "#F6661E80",
        "editor.findMatchHighlightBackground": "#201C1D40",
        "editor.findRangeHighlightBackground": "#F9CBBE75",
        "editor.hoverHighlightBackground": "#FDF0ED",
        "editor.lineHighlightBorder": "#FADAD1",
        "editorLink.activeForeground": "#DC3318",
        "editor.rangeHighlightBackground": "#DA103F15",
        "editor.snippetTabstopHighlightBackground": "#FDF0ED",
        "editor.snippetTabstopHighlightBorder": "#BDB3B1",
        "editor.snippetFinalTabstopHighlightBackground": "#FDF0ED",
        "editor.snippetFinalTabstopHighlightBorder": "#94E1B0",
        "editorWhitespace.foreground": "#201C1D1A",
        "editorIndentGuide.background": "#201C1D1A",
        "editorIndentGuide.activeBackground": "#201C1D45",
        "editorRuler.foreground": "#201C1D1A",
        "editorCodeLens.foreground": "#BDB3B1",
        "editorOverviewRuler.border": "#FDF0ED",
        "editorOverviewRuler.selectionHighlightForeground": "#F6661E",
        "editorOverviewRuler.wordHighlightForeground": "#DC3318",
        "editorOverviewRuler.wordHighlightStrongForeground": "#94E1B0",
        "editorOverviewRuler.modifiedForeground": "#DC331880",
        "editorOverviewRuler.addedForeground": "#94E1B080",
        "editorOverviewRuler.deletedForeground": "#F7939B80",
        "editorOverviewRuler.errorForeground": "#F7939B80",
        "editorOverviewRuler.warningForeground": "#F6661E80",
        "editorOverviewRuler.infoForeground": "#DC331880",
        "editorError.foreground": "#F7939B",
        "editorWarning.foreground": "#DC3318",
        "editorGutter.modifiedBackground": "#DC331880",
        "editorGutter.addedBackground": "#94E1B080",
        "editorGutter.deletedBackground": "#F7939B80",
        "gitDecoration.modifiedResourceForeground": "#DC3318",
        "gitDecoration.deletedResourceForeground": "#F7939B",
        "gitDecoration.untrackedResourceForeground": "#94E1B0",
        "gitDecoration.ignoredResourceForeground": "#BDB3B1",
        "gitDecoration.conflictingResourceForeground": "#F6661E",
        "diffEditor.insertedTextBackground": "#94E1B020",
        "diffEditor.removedTextBackground": "#F7939B50",
        "editorWidget.background": "#FDF0ED",
        "editorSuggestWidget.background": "#FDF0ED",
        "editorSuggestWidget.foreground": "#403C3D",
        "editorSuggestWidget.selectedBackground": "#FADAD1",
        "editorHoverWidget.background": "#FDF0ED",
        "editorHoverWidget.border": "#BDB3B1",
        "editorMarkerNavigation.background": "#FDF0ED",
        "peekView.border": "#FADAD1",
        "peekViewEditor.background": "#FDF0ED",
        "peekViewEditor.matchHighlightBackground": "#FBE0D980",
        "peekViewResult.background": "#FDF0ED",
        "peekViewResult.fileForeground": "#403C3D",
        "peekViewResult.lineForeground": "#403C3D",
        "peekViewResult.matchHighlightBackground": "#FBE0D980",
        "peekViewResult.selectionBackground": "#FADAD1",
        "peekViewResult.selectionForeground": "#403C3D",
        "peekViewTitle.background": "#FDF0ED",
        "peekViewTitleDescription.foreground": "#BDB3B1",
        "peekViewTitleLabel.foreground": "#403C3D",
        "merge.currentHeaderBackground": "#94E1B090",
        "merge.incomingHeaderBackground": "#DA103F90",
        "editorOverviewRuler.currentContentForeground": "#94E1B0",
        "editorOverviewRuler.incomingContentForeground": "#DA103F",
        "panel.background": "#FDF0ED",
        "panel.border": "#DA103F",
        "panelInput.border": "#403C3D",
        "panelTitle.activeBorder": "#1D8991",
        "panelTitle.activeForeground": "#403C3D",
        "panelTitle.inactiveForeground": "#BDB3B1",
        "statusBar.background": "#FDF0ED",
        "statusBar.foreground": "#403C3D",
        "statusBar.debuggingBackground": "#F7939B",
        "statusBar.debuggingForeground": "#FDF0ED",
        "statusBar.noFolderBackground": "#FDF0ED",
        "statusBar.noFolderForeground": "#403C3D",
        "statusBarItem.prominentBackground": "#F7939B",
        "statusBarItem.prominentHoverBackground": "#F6661E",
        "statusBarItem.remoteForeground": "#FDF0ED",
        "statusBarItem.remoteBackground": "#DA103F",
        "titleBar.activeBackground": "#FDF0ED",
        "titleBar.activeForeground": "#403C3D",
        "titleBar.inactiveBackground": "#FDF0ED",
        "titleBar.inactiveForeground": "#BDB3B1",
        "notification.background": "#FDF0ED",
        "notification.foreground": "#403C3D",
        "notification.buttonBackground": "#FADAD1",
        "notification.buttonForeground": "#403C3D",
        "notification.buttonHoverBackground": "#F9CBBE75",
        "notification.errorBackground": "#F7939B",
        "notification.errorForeground": "#403C3D",
        "notification.infoBackground": "#DA103F",
        "notification.infoForeground": "#FDF0ED",
        "notification.warningBackground": "#F6661E",
        "notification.warningForeground": "#FDF0ED",
        "extensionButton.prominentForeground": "#403C3D",
        "extensionButton.prominentBackground": "#94E1B090",
        "extensionButton.prominentHoverBackground": "#94E1B060",
        "pickerGroup.border": "#DA103F",
        "pickerGroup.foreground": "#DC3318",
        "debugToolBar.background": "#FDF0ED",
        "welcomePage.buttonBackground": "#FDF0ED",
        "walkThrough.embeddedEditorBackground": "#FDF0ED",
        "settings.headerForeground": "#403C3D",
        "settings.modifiedItemIndicator": "#F6661E",
        "settings.dropdownBackground": "#FDF0ED",
        "settings.dropdownForeground": "#403C3D",
        "settings.dropdownBorder": "#FDF0ED",
        "settings.checkboxBackground": "#FDF0ED",
        "settings.checkboxForeground": "#403C3D",
        "settings.checkboxBorder": "#FDF0ED",
        "checkbox.background": "#FDF0ED",
        "checkbox.foreground": "#403C3D",
        "checkbox.border": "#FDF0ED",
        "settings.textInputBackground": "#FDF0ED",
        "settings.textInputForeground": "#403C3D",
        "settings.textInputBorder": "#FDF0ED",
        "settings.numberInputBackground": "#FDF0ED",
        "settings.numberInputForeground": "#403C3D",
        "settings.numberInputBorder": "#FDF0ED",
        "breadcrumb.foreground": "#BDB3B1",
        "breadcrumb.background": "#FDF0ED",
        "breadcrumb.focusForeground": "#403C3D",
        "breadcrumb.activeSelectionForeground": "#403C3D",
        "breadcrumbPicker.background": "#FDF0ED",
        "listFilterWidget.background": "#FDF0ED",
        "listFilterWidget.outline": "#FADAD1",
        "listFilterWidget.noMatchesOutline": "#F7939B"
    },
    "tokenColors": [
        {
            "scope": [
                "emphasis"
            ],
            "settings": {
                "fontStyle": "italic"
            }
        },
        {
            "scope": [
                "strong"
            ],
            "settings": {
                "fontStyle": "bold"
            }
        },
        {
            "scope": [
                "header"
            ],
            "settings": {
                "foreground": "#DA103F"
            }
        },
        {
            "scope": [
                "source"
            ],
            "settings": {
                "foreground": "#403C3D"
            }
        },
        {
            "scope": [
                "meta.diff",
                "meta.diff.header"
            ],
            "settings": {
                "foreground": "#BDB3B1"
            }
        },
        {
            "scope": [
                "markup.inserted"
            ],
            "settings": {
                "foreground": "#94E1B0"
            }
        },
        {
            "scope": [
                "markup.deleted"
            ],
            "settings": {
                "foreground": "#F7939B"
            }
        },
        {
            "scope": [
                "markup.changed"
            ],
            "settings": {
                "foreground": "#F6661E"
            }
        },
        {
            "scope": [
                "invalid"
            ],
            "settings": {
                "foreground": "#F7939B",
                "fontStyle": "underline italic"
            }
        },
        {
            "scope": [
                "invalid.deprecated"
            ],
            "settings": {
                "foreground": "#403C3D",
                "fontStyle": "underline italic"
            }
        },
        {
            "scope": [
                "entity.name.filename"
            ],
            "settings": {
                "foreground": "#FBE0D9"
            }
        },
        {
            "scope": [
                "markup.error"
            ],
            "settings": {
                "foreground": "#F7939B"
            }
        },
        {
            "name": "Underlined markup",
            "scope": [
                "markup.underline"
            ],
            "settings": {
                "fontStyle": "underline"
            }
        },
        {
            "name": "Bold markup",
            "scope": [
                "markup.bold"
            ],
            "settings": {
                "fontStyle": "bold",
                "foreground": "#F6661E"
            }
        },
        {
            "name": "Markup headings",
            "scope": [
                "markup.heading"
            ],
            "settings": {
                "fontStyle": "bold",
                "foreground": "#DA103F"
            }
        },
        {
            "name": "Markup italic",
            "scope": [
                "markup.italic"
            ],
            "settings": {
                "foreground": "#FBE0D9",
                "fontStyle": "italic"
            }
        },
        {
            "name": "Bullets, lists (prose)",
            "scope": [
                "beginning.punctuation.definition.list.markdown",
                "beginning.punctuation.definition.quote.markdown",
                "punctuation.definition.link.restructuredtext"
            ],
            "settings": {
                "foreground": "#DC3318"
            }
        },
        {
            "name": "Inline code (prose)",
            "scope": [
                "markup.inline.raw",
                "markup.raw.restructuredtext"
            ],
            "settings": {
                "foreground": "#94E1B0"
            }
        },
        {
            "name": "Links (prose)",
            "scope": [
                "markup.underline.link",
                "markup.underline.link.image"
            ],
            "settings": {
                "foreground": "#DC3318"
            }
        },
        {
            "name": "Link text, image alt text (prose)",
            "scope": [
                "meta.link.reference.def.restructuredtext",
                "punctuation.definition.directive.restructuredtext",
                "string.other.link.description",
                "string.other.link.title"
            ],
            "settings": {
                "foreground": "#1D8991"
            }
        },
        {
            "name": "Blockquotes (prose)",
            "scope": [
                "entity.name.directive.restructuredtext",
                "markup.quote"
            ],
            "settings": {
                "foreground": "#FBE0D9",
                "fontStyle": "italic"
            }
        },
        {
            "name": "Horizontal rule (prose)",
            "scope": [
                "meta.separator.markdown"
            ],
            "settings": {
                "foreground": "#BDB3B1"
            }
        },
        {
            "name": "Code blocks",
            "scope": [
                "fenced_code.block.language",
                "markup.raw.inner.restructuredtext",
                "markup.fenced_code.block.markdown punctuation.definition.markdown"
            ],
            "settings": {
                "foreground": "#94E1B0"
            }
        },
        {
            "name": "Prose constants",
            "scope": [
                "punctuation.definition.constant.restructuredtext"
            ],
            "settings": {
                "foreground": "#DA103F"
            }
        },
        {
            "name": "Braces in markdown headings",
            "scope": [
                "markup.heading.markdown punctuation.definition.string.begin",
                "markup.heading.markdown punctuation.definition.string.end"
            ],
            "settings": {
                "foreground": "#DA103F"
            }
        },
        {
            "name": "Braces in markdown paragraphs",
            "scope": [
                "meta.paragraph.markdown punctuation.definition.string.begin",
                "meta.paragraph.markdown punctuation.definition.string.end"
            ],
            "settings": {
                "foreground": "#403C3D"
            }
        },
        {
            "name": "Braces in markdown blockquotes",
            "scope": [
                "markup.quote.markdown meta.paragraph.markdown punctuation.definition.string.begin",
                "markup.quote.markdown meta.paragraph.markdown punctuation.definition.string.end"
            ],
            "settings": {
                "foreground": "#FBE0D9"
            }
        },
        {
            "name": "User-defined class names",
            "scope": [
                "entity.name.type.class",
                "entity.name.class"
            ],
            "settings": {
                "foreground": "#DC3318",
                "fontStyle": "normal"
            }
        },
        {
            "name": "this, super, self, etc.",
            "scope": [
                "keyword.expressions-and-types.swift",
                "keyword.other.this",
                "variable.language",
                "variable.language punctuation.definition.variable.php",
                "variable.other.readwrite.instance.ruby",
                "variable.parameter.function.language.special"
            ],
            "settings": {
                "foreground": "#DA103F",
                "fontStyle": "italic"
            }
        },
        {
            "name": "Inherited classes",
            "scope": [
                "entity.other.inherited-class"
            ],
            "settings": {
                "fontStyle": "italic",
                "foreground": "#DC3318"
            }
        },
        {
            "name": "Comments",
            "scope": [
                "comment",
                "punctuation.definition.comment",
                "unused.comment",
                "wildcard.comment"
            ],
            "settings": {
                "foreground": "#BDB3B1"
            }
        },
        {
            "name": "JSDoc-style keywords",
            "scope": [
                "comment keyword.codetag.notation",
                "comment.block.documentation keyword",
                "comment.block.documentation storage.type.class"
            ],
            "settings": {
                "foreground": "#1D8991"
            }
        },
        {
            "name": "JSDoc-style types",
            "scope": [
                "comment.block.documentation entity.name.type"
            ],
            "settings": {
                "foreground": "#DC3318",
                "fontStyle": "italic"
            }
        },
        {
            "name": "JSDoc-style type brackets",
            "scope": [
                "comment.block.documentation entity.name.type punctuation.definition.bracket"
            ],
            "settings": {
                "foreground": "#DC3318"
            }
        },
        {
            "name": "JSDoc-style comment parameters",
            "scope": [
                "comment.block.documentation variable"
            ],
            "settings": {
                "foreground": "#F6661E",
                "fontStyle": "italic"
            }
        },
        {
            "name": "Constants",
            "scope": [
                "constant",
                "variable.other.constant"
            ],
            "settings": {
                "foreground": "#DA103F"
            }
        },
        {
            "name": "Constant escape sequences",
            "scope": [
                "constant.character.escape",
                "constant.character.string.escape",
                "constant.regexp"
            ],
            "settings": {
                "foreground": "#1D8991"
            }
        },
        {
            "name": "HTML tags",
            "scope": [
                "entity.name.tag"
            ],
            "settings": {
                "foreground": "#1D8991"
            }
        },
        {
            "name": "CSS attribute parent selectors ('&')",
            "scope": [
                "entity.other.attribute-name.parent-selector"
            ],
            "settings": {
                "foreground": "#1D8991"
            }
        },
        {
            "name": "HTML/CSS attribute names",
            "scope": [
                "entity.other.attribute-name"
            ],
            "settings": {
                "foreground": "#94E1B0",
                "fontStyle": "italic"
            }
        },
        {
            "name": "Function names",
            "scope": [
                "entity.name.function",
                "meta.function-call.generic",
                "meta.function-call.object",
                "meta.function-call.php",
                "meta.function-call.static",
                "meta.method-call.java meta.method",
                "meta.method.groovy",
                "support.function.any-method.lua",
                "keyword.operator.function.infix"
            ],
            "settings": {
                "foreground": "#94E1B0"
            }
        },
        {
            "name": "Function parameters",
            "scope": [
                "entity.name.variable.parameter",
                "meta.at-rule.function variable",
                "meta.at-rule.mixin variable",
                "meta.function.arguments variable.other.php",
                "meta.selectionset.graphql meta.arguments.graphql variable.arguments.graphql",
                "variable.parameter"
            ],
            "settings": {
                "fontStyle": "italic",
                "foreground": "#F6661E"
            }
        },
        {
            "name": "Decorators",
            "scope": [
                "meta.decorator variable.other.readwrite",
                "meta.decorator variable.other.property"
            ],
            "settings": {
                "foreground": "#94E1B0",
                "fontStyle": "italic"
            }
        },
        {
            "name": "Decorator Objects",
            "scope": [
                "meta.decorator variable.other.object"
            ],
            "settings": {
                "foreground": "#94E1B0"
            }
        },
        {
            "name": "Keywords",
            "scope": [
                "keyword",
                "punctuation.definition.keyword"
            ],
            "settings": {
                "foreground": "#1D8991"
            }
        },
        {
            "name": "Keyword \"new\"",
            "scope": [
                "keyword.control.new",
                "keyword.operator.new"
            ],
            "settings": {
                "fontStyle": "bold"
            }
        },
        {
            "name": "Generic selectors (CSS/SCSS/Less/Stylus)",
            "scope": [
                "meta.selector"
            ],
            "settings": {
                "foreground": "#1D8991"
            }
        },
        {
            "name": "Language Built-ins",
            "scope": [
                "support"
            ],
            "settings": {
                "fontStyle": "italic",
                "foreground": "#DC3318"
            }
        },
        {
            "name": "Built-in magic functions and constants",
            "scope": [
                "support.function.magic",
                "support.variable",
                "variable.other.predefined"
            ],
            "settings": {
                "fontStyle": "regular",
                "foreground": "#DA103F"
            }
        },
        {
            "name": "Built-in functions / properties",
            "scope": [
                "support.function",
                "support.type.property-name"
            ],
            "settings": {
                "fontStyle": "regular"
            }
        },
        {
            "name": "Separators (key/value, namespace, inheritance, pointer, hash, slice, etc)",
            "scope": [
                "constant.other.symbol.hashkey punctuation.definition.constant.ruby",
                "entity.other.attribute-name.placeholder punctuation",
                "entity.other.attribute-name.pseudo-class punctuation",
                "entity.other.attribute-name.pseudo-element punctuation",
                "meta.group.double.toml",
                "meta.group.toml",
                "meta.object-binding-pattern-variable punctuation.destructuring",
                "punctuation.colon.graphql",
                "punctuation.definition.block.scalar.folded.yaml",
                "punctuation.definition.block.scalar.literal.yaml",
                "punctuation.definition.block.sequence.item.yaml",
                "punctuation.definition.entity.other.inherited-class",
                "punctuation.function.swift",
                "punctuation.separator.dictionary.key-value",
                "punctuation.separator.hash",
                "punctuation.separator.inheritance",
                "punctuation.separator.key-value",
                "punctuation.separator.key-value.mapping.yaml",
                "punctuation.separator.namespace",
                "punctuation.separator.pointer-access",
                "punctuation.separator.slice",
                "string.unquoted.heredoc punctuation.definition.string",
                "support.other.chomping-indicator.yaml",
                "punctuation.separator.annotation"
            ],
            "settings": {
                "foreground": "#1D8991"
            }
        },
        {
            "name": "Brackets, braces, parens, etc.",
            "scope": [
                "keyword.operator.other.powershell",
                "keyword.other.statement-separator.powershell",
                "meta.brace.round",
                "meta.function-call punctuation",
                "punctuation.definition.arguments.begin",
                "punctuation.definition.arguments.end",
                "punctuation.definition.entity.begin",
                "punctuation.definition.entity.end",
                "punctuation.definition.tag.cs",
                "punctuation.definition.type.begin",
                "punctuation.definition.type.end",
                "punctuation.section.scope.begin",
                "punctuation.section.scope.end",
                "storage.type.generic.java",
                "string.template meta.brace",
                "string.template punctuation.accessor"
            ],
            "settings": {
                "foreground": "#403C3D"
            }
        },
        {
            "name": "Variable interpolation operators",
            "scope": [
                "meta.string-contents.quoted.double punctuation.definition.variable",
                "punctuation.definition.interpolation.begin",
                "punctuation.definition.interpolation.end",
                "punctuation.definition.template-expression.begin",
                "punctuation.definition.template-expression.end",
                "punctuation.section.embedded.begin",
                "punctuation.section.embedded.coffee",
                "punctuation.section.embedded.end",
                "punctuation.section.embedded.end source.php",
                "punctuation.section.embedded.end source.ruby",
                "punctuation.definition.variable.makefile"
            ],
            "settings": {
                "foreground": "#1D8991"
            }
        },
        {
            "name": "Keys (serializable languages)",
            "scope": [
                "entity.name.function.target.makefile",
                "entity.name.section.toml",
                "entity.name.tag.yaml",
                "variable.other.key.toml"
            ],
            "settings": {
                "foreground": "#DC3318"
            }
        },
        {
            "name": "Dates / timestamps (serializable languages)",
            "scope": [
                "constant.other.date",
                "constant.other.timestamp"
            ],
            "settings": {
                "foreground": "#F6661E"
            }
        },
        {
            "name": "YAML aliases",
            "scope": [
                "variable.other.alias.yaml"
            ],
            "settings": {
                "fontStyle": "italic underline",
                "foreground": "#94E1B0"
            }
        },
        {
            "name": "Storage",
            "scope": [
                "storage",
                "meta.implementation storage.type.objc",
                "meta.interface-or-protocol storage.type.objc",
                "source.groovy storage.type.def"
            ],
            "settings": {
                "fontStyle": "regular",
                "foreground": "#1D8991"
            }
        },
        {
            "name": "Types",
            "scope": [
                "entity.name.type",
                "keyword.primitive-datatypes.swift",
                "keyword.type.cs",
                "meta.protocol-list.objc",
                "meta.return-type.objc",
                "source.go storage.type",
                "source.groovy storage.type",
                "source.java storage.type",
                "source.powershell entity.other.attribute-name",
                "storage.class.std.rust",
                "storage.type.attribute.swift",
                "storage.type.c",
                "storage.type.core.rust",
                "storage.type.cs",
                "storage.type.groovy",
                "storage.type.objc",
                "storage.type.php",
                "storage.type.haskell",
                "storage.type.ocaml"
            ],
            "settings": {
                "fontStyle": "italic",
                "foreground": "#DC3318"
            }
        },
        {
            "name": "Generics, templates, and mapped type declarations",
            "scope": [
                "entity.name.type.type-parameter",
                "meta.indexer.mappedtype.declaration entity.name.type",
                "meta.type.parameters entity.name.type"
            ],
            "settings": {
                "foreground": "#F6661E"
            }
        },
        {
            "name": "Modifiers",
            "scope": [
                "storage.modifier"
            ],
            "settings": {
                "foreground": "#1D8991"
            }
        },
        {
            "name": "RegExp string",
            "scope": [
                "string.regexp",
                "constant.other.character-class.set.regexp",
                "constant.character.escape.backslash.regexp"
            ],
            "settings": {
                "foreground": "#FBE0D9"
            }
        },
        {
            "name": "Non-capture operators",
            "scope": [
                "punctuation.definition.group.capture.regexp"
            ],
            "settings": {
                "foreground": "#1D8991"
            }
        },
        {
            "name": "RegExp start and end characters",
            "scope": [
                "string.regexp punctuation.definition.string.begin",
                "string.regexp punctuation.definition.string.end"
            ],
            "settings": {
                "foreground": "#F7939B"
            }
        },
        {
            "name": "Character group",
            "scope": [
                "punctuation.definition.character-class.regexp"
            ],
            "settings": {
                "foreground": "#DC3318"
            }
        },
        {
            "name": "Capture groups",
            "scope": [
                "punctuation.definition.group.regexp"
            ],
            "settings": {
                "foreground": "#F6661E"
            }
        },
        {
            "name": "Assertion operators",
            "scope": [
                "punctuation.definition.group.assertion.regexp",
                "keyword.operator.negation.regexp"
            ],
            "settings": {
                "foreground": "#F7939B"
            }
        },
        {
            "name": "Positive lookaheads",
            "scope": [
                "meta.assertion.look-ahead.regexp"
            ],
            "settings": {
                "foreground": "#94E1B0"
            }
        },
        {
            "name": "Strings",
            "scope": [
                "string"
            ],
            "settings": {
                "foreground": "#FBE0D9"
            }
        },
        {
            "name": "String quotes (temporary vscode fix)",
            "scope": [
                "punctuation.definition.string.begin",
                "punctuation.definition.string.end"
            ],
            "settings": {
                "foreground": "#FBE0D9"
            }
        },
        {
            "name": "Property quotes (temporary vscode fix)",
            "scope": [
                "punctuation.support.type.property-name.begin",
                "punctuation.support.type.property-name.end"
            ],
            "settings": {
                "foreground": "#DA103F"
            }
        },
        {
            "name": "Docstrings",
            "scope": [
                "string.quoted.docstring.multi",
                "string.quoted.docstring.multi.python punctuation.definition.string.begin",
                "string.quoted.docstring.multi.python punctuation.definition.string.end",
                "string.quoted.docstring.multi.python constant.character.escape"
            ],
            "settings": {
                "foreground": "#BDB3B1"
            }
        },
        {
            "name": "Variables and object properties",
            "scope": [
                "variable",
                "constant.other.key.perl",
                "support.variable.property",
                "variable.other.constant.js",
                "variable.other.constant.ts",
                "variable.other.constant.tsx"
            ],
            "settings": {
                "foreground": "#403C3D"
            }
        },
        {
            "name": "Destructuring / aliasing reference name (LHS)",
            "scope": [
                "meta.import variable.other.readwrite",
                "meta.object-binding-pattern-variable variable.object.property",
                "meta.variable.assignment.destructured.object.coffee variable"
            ],
            "settings": {
                "fontStyle": "italic",
                "foreground": "#F6661E"
            }
        },
        {
            "name": "Destructuring / aliasing variable name (RHS)",
            "scope": [
                "meta.import variable.other.readwrite.alias",
                "meta.export variable.other.readwrite.alias",
                "meta.variable.assignment.destructured.object.coffee variable variable"
            ],
            "settings": {
                "fontStyle": "normal",
                "foreground": "#403C3D"
            }
        },
        {
            "name": "GraphQL keys",
            "scope": [
                "meta.selectionset.graphql variable"
            ],
            "settings": {
                "foreground": "#FBE0D9"
            }
        },
        {
            "name": "GraphQL function arguments",
            "scope": [
                "meta.selectionset.graphql meta.arguments variable"
            ],
            "settings": {
                "foreground": "#403C3D"
            }
        },
        {
            "name": "GraphQL fragment name (definition)",
            "scope": [
                "entity.name.fragment.graphql",
                "variable.fragment.graphql"
            ],
            "settings": {
                "foreground": "#DC3318"
            }
        },
        {
            "name": "Edge cases (foreground color resets)",
            "scope": [
                "constant.other.symbol.hashkey.ruby",
                "keyword.operator.dereference.java",
                "keyword.operator.navigation.groovy",
                "meta.scope.for-loop.shell punctuation.definition.string.begin",
                "meta.scope.for-loop.shell punctuation.definition.string.end",
                "meta.scope.for-loop.shell string",
                "storage.modifier.import",
                "punctuation.section.embedded.begin.tsx",
                "punctuation.section.embedded.end.tsx",
                "punctuation.section.embedded.begin.jsx",
                "punctuation.section.embedded.end.jsx",
                "punctuation.separator.list.comma.css",
                "constant.language.empty-list.haskell"
            ],
            "settings": {
                "foreground": "#403C3D"
            }
        },
        {
            "name": "Shell variables prefixed with \"$\" (edge case)",
            "scope": [
                "source.shell variable.other"
            ],
            "settings": {
                "foreground": "#DA103F"
            }
        },
        {
            "name": "Powershell constants mistakenly scoped to `support`, rather than `constant` (edge)",
            "scope": [
                "support.constant"
            ],
            "settings": {
                "fontStyle": "normal",
                "foreground": "#DA103F"
            }
        },
        {
            "name": "Makefile prerequisite names",
            "scope": [
                "meta.scope.prerequisites.makefile"
            ],
            "settings": {
                "foreground": "#FBE0D9"
            }
        },
        {
            "name": "SCSS attibute selector strings",
            "scope": [
                "meta.attribute-selector.scss"
            ],
            "settings": {
                "foreground": "#FBE0D9"
            }
        },
        {
            "name": "SCSS attribute selector brackets",
            "scope": [
                "punctuation.definition.attribute-selector.end.bracket.square.scss",
                "punctuation.definition.attribute-selector.begin.bracket.square.scss"
            ],
            "settings": {
                "foreground": "#403C3D"
            }
        },
        {
            "name": "Haskell Pragmas",
            "scope": [
                "meta.preprocessor.haskell"
            ],
            "settings": {
                "foreground": "#BDB3B1"
            }
        }
    ]
}